stackstream/__init__.py
stackstream/api.py
stackstream/cli.py
stackstream/helpers.py
stackstream-0.1.1.dist-info/LICENSE
stackstream-0.1.1.dist-info/METADATA
stackstream-0.1.1.dist-info/WHEEL
stackstream-0.1.1.dist-info/entry_points.txt
stackstream-0.1.1.dist-info/top_level.txt
stackstream-0.1.1.dist-info/RECORD
