Metadata-Version: 2.1
Name: stackstream
Version: 0.1.1
Summary: Enhanced Git workflow tools
Home-page: https://github.com/findjashua/stackstream
Author: Jashua Gupta
Author-email: findjashua@gmail.com
Classifier: Development Status :: 3 - Alpha
Classifier: Intended Audience :: Developers
Classifier: License :: OSI Approved :: MIT License
Classifier: Operating System :: OS Independent
Classifier: Programming Language :: Python :: 3
Classifier: Programming Language :: Python :: 3.6
Classifier: Programming Language :: Python :: 3.7
Classifier: Programming Language :: Python :: 3.8
Classifier: Programming Language :: Python :: 3.9
Requires-Python: >=3.6
License-File: LICENSE
